pytomlpp-1.0.13.dist-info/LICENSE
pytomlpp-1.0.13.dist-info/WHEEL
pytomlpp-1.0.13.dist-info/top_level.txt
pytomlpp-1.0.13.dist-info/RECORD
pytomlpp-1.0.13.dist-info/METADATA
pytomlpp/_io.py
pytomlpp/__init__.py
pytomlpp/_impl.cpython-39-x86_64-linux-gnu.so
pytomlpp/_impl.pyi
pytomlpp/py.typed
