Metadata-Version: 2.1
Name: pytomlpp
Version: 1.0.13
Summary: A python wrapper for toml++
Home-page: UNKNOWN
Author: Bob Fang
Author-email: bob.fang.london@gmail.com
License: UNKNOWN
Project-URL: Source, https://github.com/bobfang1992/pytomlpp
Project-URL: Tracker, https://github.com/bobfang1992/pytomlpp/issues
Keywords: toml,parser,serilization,deserialization,serdes
Platform: UNKNOWN
Classifier: Development Status :: 5 - Production/Stable
Classifier: Operating System :: OS Independent
Classifier: Programming Language :: Python
Classifier: Programming Language :: Python :: 3
Classifier: Programming Language :: Python :: 3.7
Classifier: Programming Language :: Python :: 3.8
Classifier: Programming Language :: Python :: 3.9
Classifier: Programming Language :: Python :: 3.10
Classifier: Programming Language :: Python :: 3.11
Classifier: Intended Audience :: Developers
Classifier: License :: OSI Approved :: MIT License
Classifier: Natural Language :: English
Classifier: Topic :: Utilities
License-File: LICENSE
